<?xml version="1.0" encoding="UTF-8" standalone="yes"?>
<instrumentRecording>
  <globalParameter>
    <audioFileName>G53-48108-1111-00087.wav</audioFileName>
    <instrument>EGUI</instrument>
    <recordingDate>07.01.2013</recordingDate>
  </globalParameter>
  <transcription>
    <event>
      <pitch>48</pitch>
      <onsetSec>0.236</onsetSec>
      <offsetSec>2.5</offsetSec>
      <fretNumber>8</fretNumber>
      <stringNumber>1</stringNumber>
      <excitationStyle>PK</excitationStyle>
      <expressionStyle>NO</expressionStyle>
    </event>
  </transcription>
</instrumentRecording> 
